vquesrs/__init__.py
vquesrs-0.0.3.dist-info/METADATA
vquesrs-0.0.3.dist-info/WHEEL
vquesrs-0.0.3.dist-info/top_level.txt
vquesrs-0.0.3.dist-info/RECORD
