Metadata-Version: 2.1
Name: vquesrs
Version: 0.0.3
Summary: Everything you need for data mining and scraping in Python
Home-page: https://github.com/PyGera/vquesrs/
Author: Federico Gerardi
Author-email: me@federicogerardi.it
License: UNKNOWN
Platform: UNKNOWN
